pedtools/__init__.py
pedtools-0.0.1.dev2.dist-info/LICENCE
pedtools-0.0.1.dev2.dist-info/METADATA
pedtools-0.0.1.dev2.dist-info/WHEEL
pedtools-0.0.1.dev2.dist-info/entry_points.txt
pedtools-0.0.1.dev2.dist-info/top_level.txt
pedtools-0.0.1.dev2.dist-info/RECORD
